{
  "protocol_version" : "0.0.6",
  "configuration" : {
    "version" : "(6.13.0) (explicit/664fdcba172)",
    "tlc" : "__thread",
    "sigsgev" : "normal",
    "notifications" : "kqueue",
    "architecture" : "arm64",
    "disabled_features" : "com,shared_perfcounters",
    "smallconfig" : "disabled",
    "bigarrays" : "disabled",
    "softdebug" : "enabled",
    "interpreter" : "enabled",
    "llvm_support" : "disabled",
    "suspend" : "preemptive"
  },
  "memory" : {
    "Resident Size" : "530923520",
    "Virtual Size" : "422468894720",
    "minor_gc_time" : "0",
    "major_gc_time" : "14225319",
    "minor_gc_count" : "0",
    "major_gc_count" : "163",
    "major_gc_time_concurrent" : "0"
 },
  "threads" : [
 {
    "is_managed" : false,
    "offset_free_hash" : "0x0",
    "offset_rich_hash" : "0x0",
    "crashed" : false,
    "native_thread_id" : "0x17dec7000",
    "thread_info_addr" : "0x15a0db800",
    "thread_name" : "Debugger agent",
    "ctx" : {
      "IP" : "0x1c417ee84",
      "SP" : "0x17dec6aa0",
      "BP" : "0x17dec6ae0"
  },
    "unmanaged_frames" : [
  {
      "is_managed" : "false",
      "native_address" : "0x13d705c4c",
      "native_offset" : "0x00000"
   }
,
  {
      "is_managed" : "false",
      "native_address" : "0x13d83c788",
      "native_offset" : "0x00000"
   }
,
  {
      "is_managed" : "false",
      "native_address" : "0x13d83cae4",
      "native_offset" : "0x00000"
   }
,
  {
      "is_managed" : "false",
      "native_address" : "0x13d83c8ac",
      "native_offset" : "0x00000"
   }
,
  {
      "is_managed" : "false",
      "native_address" : "0x13d746bd4",
      "native_offset" : "0x00000"
   }
,
  {
      "is_managed" : "false",
      "native_address" : "0x1c41cb4a4",
      "native_offset" : "0x00000"
   }
,
  {
      "is_managed" : "false",
      "native_address" : "0x13d77c3e0",
      "native_offset" : "0x00000"
   }
,
  {
      "is_managed" : "false",
      "native_address" : "0x13d773760",
      "native_offset" : "0x00000"
   }
,
  {
      "is_managed" : "false",
      "native_address" : "0x13d83d4f4",
      "native_offset" : "0x00000"
   }
,
  {
      "is_managed" : "false",
      "native_address" : "0x13d83d3a0",
      "native_offset" : "0x00000"
   }
,
  {
      "is_managed" : "false",
      "native_address" : "0x13d8bccb0",
      "native_offset" : "0x00000"
   }
,
  {
      "is_managed" : "false",
      "native_address" : "0x13d8bcc38",
      "native_offset" : "0x00000"
   }
,
  {
      "is_managed" : "false",
      "native_address" : "0x1c41b426c",
      "native_offset" : "0x00000"
   }
,
  {
      "is_managed" : "false",
      "native_address" : "0x1c41af08c",
      "native_offset" : "0x00000"
   }

  ]
 },
 {
    "is_managed" : false,
    "offset_free_hash" : "0x0",
    "offset_rich_hash" : "0x0",
    "crashed" : false,
    "native_thread_id" : "0x29ea63000",
    "thread_info_addr" : "0x2a6265400",
    "thread_name" : "Thread Pool Worker",
    "ctx" : {
      "IP" : "0x1c4176904",
      "SP" : "0x29ea62db0",
      "BP" : "0x29ea62e50"
  },
    "unmanaged_frames" : [
  {
      "is_managed" : "false",
      "native_address" : "0x13d705c4c",
      "native_offset" : "0x00000"
   }
,
  {
      "is_managed" : "false",
      "native_address" : "0x13d83c788",
      "native_offset" : "0x00000"
   }
,
  {
      "is_managed" : "false",
      "native_address" : "0x13d83cae4",
      "native_offset" : "0x00000"
   }
,
  {
      "is_managed" : "false",
      "native_address" : "0x13d83c8ac",
      "native_offset" : "0x00000"
   }
,
  {
      "is_managed" : "false",
      "native_address" : "0x13d746bd4",
      "native_offset" : "0x00000"
   }
,
  {
      "is_managed" : "false",
      "native_address" : "0x1c41cb4a4",
      "native_offset" : "0x00000"
   }
,
  {
      "is_managed" : "false",
      "native_address" : "0x13d794c70",
      "native_offset" : "0x00000"
   }
,
  {
      "is_managed" : "false",
      "native_address" : "0x13d83d4f4",
      "native_offset" : "0x00000"
   }
,
  {
      "is_managed" : "false",
      "native_address" : "0x13d83d3a0",
      "native_offset" : "0x00000"
   }
,
  {
      "is_managed" : "false",
      "native_address" : "0x13d8bccb0",
      "native_offset" : "0x00000"
   }
,
  {
      "is_managed" : "false",
      "native_address" : "0x13d8bcc38",
      "native_offset" : "0x00000"
   }
,
  {
      "is_managed" : "false",
      "native_address" : "0x1c41b426c",
      "native_offset" : "0x00000"
   }
,
  {
      "is_managed" : "false",
      "native_address" : "0x1c41af08c",
      "native_offset" : "0x00000"
   }

  ]
 },
 {
    "is_managed" : true,
    "offset_free_hash" : "0xa56977278",
    "offset_rich_hash" : "0xa56977609",
    "crashed" : true,
    "native_thread_id" : "0x10a750580",
    "thread_info_addr" : "0x15b0bba00",
    "thread_name" : "tid_103",
    "ctx" : {
      "IP" : "0x1051711f0",
      "SP" : "0x16b6bed40",
      "BP" : "0x16b6bed80"
  },
    "managed_frames" : [
  {
      "is_managed" : "false",
      "native_address" : "unregistered"
   }
,
  {
      "is_managed" : "true",
      "guid" : "3C33AE56-05E2-439A-AE7B-A0A2201A87A6",
      "token" : "0x00000",
      "native_offset" : "0x0",
      "filename" : "UnityEditor.CoreModule.dll",
      "sizeofimage" : "0x81a000",
      "timestamp" : "0xf67557a6",
      "il_offset" : "0xffffffff"
   }
,
  {
      "is_managed" : "true",
      "guid" : "3C33AE56-05E2-439A-AE7B-A0A2201A87A6",
      "token" : "0x6007ece",
      "native_offset" : "0x0",
      "filename" : "UnityEditor.CoreModule.dll",
      "sizeofimage" : "0x81a000",
      "timestamp" : "0xf67557a6",
      "il_offset" : "0x00001"
   }
,
  {
      "is_managed" : "true",
      "guid" : "3C33AE56-05E2-439A-AE7B-A0A2201A87A6",
      "token" : "0x6007f35",
      "native_offset" : "0x0",
      "filename" : "UnityEditor.CoreModule.dll",
      "sizeofimage" : "0x81a000",
      "timestamp" : "0xf67557a6",
      "il_offset" : "0x00317"
   }
,
  {
      "is_managed" : "true",
      "guid" : "3C33AE56-05E2-439A-AE7B-A0A2201A87A6",
      "token" : "0x6007dc9",
      "native_offset" : "0x0",
      "filename" : "UnityEditor.CoreModule.dll",
      "sizeofimage" : "0x81a000",
      "timestamp" : "0xf67557a6",
      "il_offset" : "0x0000e"
   }
,
  {
      "is_managed" : "true",
      "guid" : "3C33AE56-05E2-439A-AE7B-A0A2201A87A6",
      "token" : "0x6007db3",
      "native_offset" : "0x0",
      "filename" : "UnityEditor.CoreModule.dll",
      "sizeofimage" : "0x81a000",
      "timestamp" : "0xf67557a6",
      "il_offset" : "0x00041"
   }
,
  {
      "is_managed" : "true",
      "guid" : "3C33AE56-05E2-439A-AE7B-A0A2201A87A6",
      "token" : "0x6001f4e",
      "native_offset" : "0x0",
      "filename" : "UnityEditor.CoreModule.dll",
      "sizeofimage" : "0x81a000",
      "timestamp" : "0xf67557a6",
      "il_offset" : "0x00001"
   }
,
  {
      "is_managed" : "true",
      "guid" : "612A2C65-AAF8-43D6-98F8-D38B2AD7654A",
      "token" : "0x00000",
      "native_offset" : "0x0",
      "filename" : "mscorlib.dll",
      "sizeofimage" : "0x470000",
      "timestamp" : "0xd0713de6",
      "il_offset" : "0x0002a"
   }

  ],
  "unmanaged_frames" : [
 {
    "is_managed" : "false",
    "native_address" : "0x13d705c4c",
    "native_offset" : "0x00000"
  }
,
 {
    "is_managed" : "false",
    "native_address" : "0x13d83c788",
    "native_offset" : "0x00000"
  }
,
 {
    "is_managed" : "false",
    "native_address" : "0x13d83cae4",
    "native_offset" : "0x00000"
  }
,
 {
    "is_managed" : "false",
    "native_address" : "0x13d83d0d4",
    "native_offset" : "0x00000"
  }
,
 {
    "is_managed" : "false",
    "native_address" : "0x13d747a20",
    "native_offset" : "0x00000"
  }
,
 {
    "is_managed" : "false",
    "native_address" : "0x13d709d58",
    "native_offset" : "0x00000"
  }
,
 {
    "is_managed" : "false",
    "native_address" : "0x13d692620",
    "native_offset" : "0x00000"
  }
,
 {
    "is_managed" : "false",
    "native_address" : "0x1c41cb4a4",
    "native_offset" : "0x00000"
  }
,
 {
    "is_managed" : "false",
    "native_address" : "0x105715b00",
    "native_offset" : "0x00000"
  }
,
 {
    "is_managed" : "false",
    "native_address" : "0x105715b00",
    "native_offset" : "0x00000"
  }
,
 {
    "is_managed" : "false",
    "native_address" : "0x1065daeb8",
    "native_offset" : "0x00000"
  }
,
 {
    "is_managed" : "false",
    "native_address" : "0x106654b48",
    "native_offset" : "0x00000"
  }
,
 {
    "is_managed" : "false",
    "native_address" : "0x1066564e4",
    "native_offset" : "0x00000"
  }
,
 {
    "is_managed" : "false",
    "native_address" : "0x1066fd9b0",
    "native_offset" : "0x00000"
  }
,
 {
    "is_managed" : "false",
    "native_address" : "0x1066d625c",
    "native_offset" : "0x00000"
  }
,
 {
    "is_managed" : "false",
    "native_address" : "0x105f93bd0",
    "native_offset" : "0x00000"
  }
,
 {
    "is_managed" : "false",
    "native_address" : "0x105f94968",
    "native_offset" : "0x00000"
  }
,
 {
    "is_managed" : "false",
    "native_address" : "0x105f951f8",
    "native_offset" : "0x00000"
  }
,
 {
    "is_managed" : "false",
    "native_address" : "0x106206b00",
    "native_offset" : "0x00000"
  }
,
 {
    "is_managed" : "false",
    "native_address" : "0x105cf1ce8",
    "native_offset" : "0x00000"
  }
,
 {
    "is_managed" : "false",
    "native_address" : "0x104ab345c",
    "native_offset" : "0x00000"
  }
,
 {
    "is_managed" : "true",
    "guid" : "3C33AE56-05E2-439A-AE7B-A0A2201A87A6",
    "token" : "0x00000",
    "native_offset" : "0x0",
    "filename" : "UnityEditor.CoreModule.dll",
    "sizeofimage" : "0x81a000",
    "timestamp" : "0xf67557a6",
    "il_offset" : "0x00000"
  }
,
 {
    "is_managed" : "true",
    "guid" : "3C33AE56-05E2-439A-AE7B-A0A2201A87A6",
    "token" : "0x6007ece",
    "native_offset" : "0x0",
    "filename" : "UnityEditor.CoreModule.dll",
    "sizeofimage" : "0x81a000",
    "timestamp" : "0xf67557a6",
    "il_offset" : "0x00000"
  }
,
 {
    "is_managed" : "true",
    "guid" : "3C33AE56-05E2-439A-AE7B-A0A2201A87A6",
    "token" : "0x6007f35",
    "native_offset" : "0x0",
    "filename" : "UnityEditor.CoreModule.dll",
    "sizeofimage" : "0x81a000",
    "timestamp" : "0xf67557a6",
    "il_offset" : "0x00000"
  }
,
 {
    "is_managed" : "true",
    "guid" : "3C33AE56-05E2-439A-AE7B-A0A2201A87A6",
    "token" : "0x6007dc9",
    "native_offset" : "0x0",
    "filename" : "UnityEditor.CoreModule.dll",
    "sizeofimage" : "0x81a000",
    "timestamp" : "0xf67557a6",
    "il_offset" : "0x00000"
  }
,
 {
    "is_managed" : "true",
    "guid" : "3C33AE56-05E2-439A-AE7B-A0A2201A87A6",
    "token" : "0x6007db3",
    "native_offset" : "0x0",
    "filename" : "UnityEditor.CoreModule.dll",
    "sizeofimage" : "0x81a000",
    "timestamp" : "0xf67557a6",
    "il_offset" : "0x00000"
  }
,
 {
    "is_managed" : "true",
    "guid" : "3C33AE56-05E2-439A-AE7B-A0A2201A87A6",
    "token" : "0x6001f4e",
    "native_offset" : "0x0",
    "filename" : "UnityEditor.CoreModule.dll",
    "sizeofimage" : "0x81a000",
    "timestamp" : "0xf67557a6",
    "il_offset" : "0x00000"
  }
,
 {
    "is_managed" : "true",
    "guid" : "612A2C65-AAF8-43D6-98F8-D38B2AD7654A",
    "token" : "0x00000",
    "native_offset" : "0x0",
    "filename" : "mscorlib.dll",
    "sizeofimage" : "0x470000",
    "timestamp" : "0xd0713de6",
    "il_offset" : "0x00000"
  }
,
 {
    "is_managed" : "false",
    "native_address" : "0x13d6958e0",
    "native_offset" : "0x00000"
  }
,
 {
    "is_managed" : "false",
    "native_address" : "0x13d81b6a8",
    "native_offset" : "0x00000"
  }
,
 {
    "is_managed" : "false",
    "native_address" : "0x13d81b5c8",
    "native_offset" : "0x00000"
  }
,
 {
    "is_managed" : "false",
    "native_address" : "0x10538e068",
    "native_offset" : "0x00000"
  }
,
 {
    "is_managed" : "false",
    "native_address" : "0x10536bea0",
    "native_offset" : "0x00000"
  }
,
 {
    "is_managed" : "false",
    "native_address" : "0x105498b9c",
    "native_offset" : "0x00000"
  }
,
 {
    "is_managed" : "false",
    "native_address" : "0x105dfb2b4",
    "native_offset" : "0x00000"
  }
,
 {
    "is_managed" : "false",
    "native_address" : "0x106fd3b98",
    "native_offset" : "0x00000"
  }
,
 {
    "is_managed" : "false",
    "native_address" : "0x106d0fb18",
    "native_offset" : "0x00000"
  }
,
 {
    "is_managed" : "false",
    "native_address" : "0x106d0fe6c",
    "native_offset" : "0x00000"
  }
,
 {
    "is_managed" : "false",
    "native_address" : "0x106d0fc54",
    "native_offset" : "0x00000"
  }
,
 {
    "is_managed" : "false",
    "native_address" : "0x106fd3a74",
    "native_offset" : "0x00000"
  }
,
 {
    "is_managed" : "false",
    "native_address" : "0x106fce3d0",
    "native_offset" : "0x00000"
  }
,
 {
    "is_managed" : "false",
    "native_address" : "0x106fce524",
    "native_offset" : "0x00000"
  }
,
 {
    "is_managed" : "false",
    "native_address" : "0x1c7554684",
    "native_offset" : "0x00000"
  }
,
 {
    "is_managed" : "false",
    "native_address" : "0x1c6f540e0",
    "native_offset" : "0x00000"
  }
,
 {
    "is_managed" : "false",
    "native_address" : "0x106fbf3e0",
    "native_offset" : "0x00000"
  }
,
 {
    "is_managed" : "false",
    "native_address" : "0x106fc27a4",
    "native_offset" : "0x00000"
  }
,
 {
    "is_managed" : "false",
    "native_address" : "0x1c51a5950",
    "native_offset" : "0x00000"
  }
,
 {
    "is_managed" : "false",
    "native_address" : "0x1c429b954",
    "native_offset" : "0x00000"
  }
,
 {
    "is_managed" : "false",
    "native_address" : "0x1c429b53c",
    "native_offset" : "0x00000"
  }
,
 {
    "is_managed" : "false",
    "native_address" : "0x1c429afc4",
    "native_offset" : "0x00000"
  }
,
 {
    "is_managed" : "false",
    "native_address" : "0x1c427fa54",
    "native_offset" : "0x00000"
  }
,
 {
    "is_managed" : "false",
    "native_address" : "0x1c427eb24",
    "native_offset" : "0x00000"
  }
,
 {
    "is_managed" : "false",
    "native_address" : "0x1cceb7338",
    "native_offset" : "0x00000"
  }
,
 {
    "is_managed" : "false",
    "native_address" : "0x1cceb6fc4",
    "native_offset" : "0x00000"
  }
,
 {
    "is_managed" : "false",
    "native_address" : "0x1cceb6e68",
    "native_offset" : "0x00000"
  }
,
 {
    "is_managed" : "false",
    "native_address" : "0x1c6de578c",
    "native_offset" : "0x00000"
  }
,
 {
    "is_managed" : "false",
    "native_address" : "0x1c6de4084",
    "native_offset" : "0x00000"
  }
,
 {
    "is_managed" : "false",
    "native_address" : "0x1c6dd6250",
    "native_offset" : "0x00000"
  }
,
 {
    "is_managed" : "false",
    "native_address" : "0x1c6da796c",
    "native_offset" : "0x00000"
  }
,
 {
    "is_managed" : "false",
    "native_address" : "0x106fbfaf4",
    "native_offset" : "0x00000"
  }
,
 {
    "is_managed" : "false",
    "native_address" : "0x106fbfe2c",
    "native_offset" : "0x00000"
  }
,
 {
    "is_managed" : "false",
    "native_address" : "0x10a6dd08c",
    "native_offset" : "0x00000"
  }

 ]
},
{
  "is_managed" : false,
  "offset_free_hash" : "0x0",
  "offset_rich_hash" : "0x0",
  "crashed" : false,
  "native_thread_id" : "0x29cccb000",
  "thread_info_addr" : "0x12a75d600",
  "thread_name" : "tid_3bd63",
  "ctx" : {
    "IP" : "0x1c417a270",
    "SP" : "0x29cccac20",
    "BP" : "0x29cccacb0"
 },
  "unmanaged_frames" : [
 {
    "is_managed" : "false",
    "native_address" : "0x13d705c4c",
    "native_offset" : "0x00000"
  }
,
 {
    "is_managed" : "false",
    "native_address" : "0x13d83c788",
    "native_offset" : "0x00000"
  }
,
 {
    "is_managed" : "false",
    "native_address" : "0x13d83cae4",
    "native_offset" : "0x00000"
  }
,
 {
    "is_managed" : "false",
    "native_address" : "0x13d83c8ac",
    "native_offset" : "0x00000"
  }
,
 {
    "is_managed" : "false",
    "native_address" : "0x13d746bd4",
    "native_offset" : "0x00000"
  }
,
 {
    "is_managed" : "false",
    "native_address" : "0x1c41cb4a4",
    "native_offset" : "0x00000"
  }
,
 {
    "is_managed" : "false",
    "native_address" : "0x1c41b4868",
    "native_offset" : "0x00000"
  }
,
 {
    "is_managed" : "false",
    "native_address" : "0x13d88be08",
    "native_offset" : "0x00000"
  }
,
 {
    "is_managed" : "false",
    "native_address" : "0x13d895ae4",
    "native_offset" : "0x00000"
  }
,
 {
    "is_managed" : "false",
    "native_address" : "0x13d794478",
    "native_offset" : "0x00000"
  }
,
 {
    "is_managed" : "false",
    "native_address" : "0x13d83d4f4",
    "native_offset" : "0x00000"
  }
,
 {
    "is_managed" : "false",
    "native_address" : "0x13d83d3a0",
    "native_offset" : "0x00000"
  }
,
 {
    "is_managed" : "false",
    "native_address" : "0x13d8bccb0",
    "native_offset" : "0x00000"
  }
,
 {
    "is_managed" : "false",
    "native_address" : "0x13d8bcc38",
    "native_offset" : "0x00000"
  }
,
 {
    "is_managed" : "false",
    "native_address" : "0x1c41b426c",
    "native_offset" : "0x00000"
  }
,
 {
    "is_managed" : "false",
    "native_address" : "0x1c41af08c",
    "native_offset" : "0x00000"
  }

 ]
},
{
  "is_managed" : true,
  "offset_free_hash" : "0xfb24c93e6",
  "offset_rich_hash" : "0xfb24c956f",
  "crashed" : false,
  "native_thread_id" : "0x29d79b000",
  "thread_info_addr" : "0x139c2ea00",
  "thread_name" : "tid_391df",
  "ctx" : {
    "IP" : "0x1c417a270",
    "SP" : "0x29d79a3b0",
    "BP" : "0x29d79a440"
 },
  "managed_frames" : [
 {
    "is_managed" : "false",
    "native_address" : "unregistered"
  }
,
 {
    "is_managed" : "true",
    "guid" : "612A2C65-AAF8-43D6-98F8-D38B2AD7654A",
    "token" : "0x00000",
    "native_offset" : "0x0",
    "filename" : "mscorlib.dll",
    "sizeofimage" : "0x470000",
    "timestamp" : "0xd0713de6",
    "il_offset" : "0xffffffff"
  }
,
 {
    "is_managed" : "true",
    "guid" : "612A2C65-AAF8-43D6-98F8-D38B2AD7654A",
    "token" : "0x6001f5d",
    "native_offset" : "0x0",
    "filename" : "mscorlib.dll",
    "sizeofimage" : "0x470000",
    "timestamp" : "0xd0713de6",
    "il_offset" : "0x0002f"
  }
,
 {
    "is_managed" : "true",
    "guid" : "612A2C65-AAF8-43D6-98F8-D38B2AD7654A",
    "token" : "0x6001f50",
    "native_offset" : "0x0",
    "filename" : "mscorlib.dll",
    "sizeofimage" : "0x470000",
    "timestamp" : "0xd0713de6",
    "il_offset" : "0x0000e"
  }
,
 {
    "is_managed" : "true",
    "guid" : "612A2C65-AAF8-43D6-98F8-D38B2AD7654A",
    "token" : "0x6001f52",
    "native_offset" : "0x0",
    "filename" : "mscorlib.dll",
    "sizeofimage" : "0x470000",
    "timestamp" : "0xd0713de6",
    "il_offset" : "0x00000"
  }
,
 {
    "is_managed" : "true",
    "guid" : "EB829DFF-9616-411E-83EC-5826A0DB50FA",
    "token" : "0x6005a11",
    "native_offset" : "0x0",
    "filename" : "unityplastic.dll",
    "sizeofimage" : "0x4ec000",
    "timestamp" : "0x62c604f1",
    "il_offset" : "0x00030"
  }
,
 {
    "is_managed" : "true",
    "guid" : "612A2C65-AAF8-43D6-98F8-D38B2AD7654A",
    "token" : "0x6001f7d",
    "native_offset" : "0x0",
    "filename" : "mscorlib.dll",
    "sizeofimage" : "0x470000",
    "timestamp" : "0xd0713de6",
    "il_offset" : "0x00014"
  }
,
 {
    "is_managed" : "true",
    "guid" : "612A2C65-AAF8-43D6-98F8-D38B2AD7654A",
    "token" : "0x6001f25",
    "native_offset" : "0x0",
    "filename" : "mscorlib.dll",
    "sizeofimage" : "0x470000",
    "timestamp" : "0xd0713de6",
    "il_offset" : "0x00071"
  }
,
 {
    "is_managed" : "true",
    "guid" : "612A2C65-AAF8-43D6-98F8-D38B2AD7654A",
    "token" : "0x6001f23",
    "native_offset" : "0x0",
    "filename" : "mscorlib.dll",
    "sizeofimage" : "0x470000",
    "timestamp" : "0xd0713de6",
    "il_offset" : "0x00000"
  }
,
 {
    "is_managed" : "true",
    "guid" : "612A2C65-AAF8-43D6-98F8-D38B2AD7654A",
    "token" : "0x6001f22",
    "native_offset" : "0x0",
    "filename" : "mscorlib.dll",
    "sizeofimage" : "0x470000",
    "timestamp" : "0xd0713de6",
    "il_offset" : "0x0002b"
  }
,
 {
    "is_managed" : "true",
    "guid" : "612A2C65-AAF8-43D6-98F8-D38B2AD7654A",
    "token" : "0x6001f7f",
    "native_offset" : "0x0",
    "filename" : "mscorlib.dll",
    "sizeofimage" : "0x470000",
    "timestamp" : "0xd0713de6",
    "il_offset" : "0x00008"
  }
,
 {
    "is_managed" : "true",
    "guid" : "612A2C65-AAF8-43D6-98F8-D38B2AD7654A",
    "token" : "0x00000",
    "native_offset" : "0x0",
    "filename" : "mscorlib.dll",
    "sizeofimage" : "0x470000",
    "timestamp" : "0xd0713de6",
    "il_offset" : "0x00065"
  }

 ],
"unmanaged_frames" : [
{
  "is_managed" : "false",
  "native_address" : "0x13d705c4c",
  "native_offset" : "0x00000"
 }
,
{
  "is_managed" : "false",
  "native_address" : "0x13d83c788",
  "native_offset" : "0x00000"
 }
,
{
  "is_managed" : "false",
  "native_address" : "0x13d83cae4",
  "native_offset" : "0x00000"
 }
,
{
  "is_managed" : "false",
  "native_address" : "0x13d83c8ac",
  "native_offset" : "0x00000"
 }
,
{
  "is_managed" : "false",
  "native_address" : "0x13d746bd4",
  "native_offset" : "0x00000"
 }
,
{
  "is_managed" : "false",
  "native_address" : "0x1c41cb4a4",
  "native_offset" : "0x00000"
 }
,
{
  "is_managed" : "false",
  "native_address" : "0x1c41b4868",
  "native_offset" : "0x00000"
 }
,
{
  "is_managed" : "false",
  "native_address" : "0x13d88be08",
  "native_offset" : "0x00000"
 }
,
{
  "is_managed" : "false",
  "native_address" : "0x13d8484b0",
  "native_offset" : "0x00000"
 }
,
{
  "is_managed" : "false",
  "native_address" : "0x13d8482e4",
  "native_offset" : "0x00000"
 }
,
{
  "is_managed" : "false",
  "native_address" : "0x13d8775d8",
  "native_offset" : "0x00000"
 }
,
{
  "is_managed" : "false",
  "native_address" : "0x13d7e0c8c",
  "native_offset" : "0x00000"
 }
,
{
  "is_managed" : "true",
  "guid" : "612A2C65-AAF8-43D6-98F8-D38B2AD7654A",
  "token" : "0x00000",
  "native_offset" : "0x0",
  "filename" : "mscorlib.dll",
  "sizeofimage" : "0x470000",
  "timestamp" : "0xd0713de6",
  "il_offset" : "0x00000"
 }
,
{
  "is_managed" : "true",
  "guid" : "612A2C65-AAF8-43D6-98F8-D38B2AD7654A",
  "token" : "0x6001f5d",
  "native_offset" : "0x0",
  "filename" : "mscorlib.dll",
  "sizeofimage" : "0x470000",
  "timestamp" : "0xd0713de6",
  "il_offset" : "0x00000"
 }
,
{
  "is_managed" : "true",
  "guid" : "612A2C65-AAF8-43D6-98F8-D38B2AD7654A",
  "token" : "0x6001f50",
  "native_offset" : "0x0",
  "filename" : "mscorlib.dll",
  "sizeofimage" : "0x470000",
  "timestamp" : "0xd0713de6",
  "il_offset" : "0x00000"
 }
,
{
  "is_managed" : "true",
  "guid" : "612A2C65-AAF8-43D6-98F8-D38B2AD7654A",
  "token" : "0x6001f52",
  "native_offset" : "0x0",
  "filename" : "mscorlib.dll",
  "sizeofimage" : "0x470000",
  "timestamp" : "0xd0713de6",
  "il_offset" : "0x00000"
 }
,
{
  "is_managed" : "true",
  "guid" : "EB829DFF-9616-411E-83EC-5826A0DB50FA",
  "token" : "0x6005a11",
  "native_offset" : "0x0",
  "filename" : "unityplastic.dll",
  "sizeofimage" : "0x4ec000",
  "timestamp" : "0x62c604f1",
  "il_offset" : "0x00000"
 }
,
{
  "is_managed" : "true",
  "guid" : "612A2C65-AAF8-43D6-98F8-D38B2AD7654A",
  "token" : "0x6001f7d",
  "native_offset" : "0x0",
  "filename" : "mscorlib.dll",
  "sizeofimage" : "0x470000",
  "timestamp" : "0xd0713de6",
  "il_offset" : "0x00000"
 }
,
{
  "is_managed" : "true",
  "guid" : "612A2C65-AAF8-43D6-98F8-D38B2AD7654A",
  "token" : "0x6001f25",
  "native_offset" : "0x0",
  "filename" : "mscorlib.dll",
  "sizeofimage" : "0x470000",
  "timestamp" : "0xd0713de6",
  "il_offset" : "0x00000"
 }
,
{
  "is_managed" : "true",
  "guid" : "612A2C65-AAF8-43D6-98F8-D38B2AD7654A",
  "token" : "0x6001f23",
  "native_offset" : "0x0",
  "filename" : "mscorlib.dll",
  "sizeofimage" : "0x470000",
  "timestamp" : "0xd0713de6",
  "il_offset" : "0x00000"
 }
,
{
  "is_managed" : "true",
  "guid" : "612A2C65-AAF8-43D6-98F8-D38B2AD7654A",
  "token" : "0x6001f22",
  "native_offset" : "0x0",
  "filename" : "mscorlib.dll",
  "sizeofimage" : "0x470000",
  "timestamp" : "0xd0713de6",
  "il_offset" : "0x00000"
 }
,
{
  "is_managed" : "true",
  "guid" : "612A2C65-AAF8-43D6-98F8-D38B2AD7654A",
  "token" : "0x6001f7f",
  "native_offset" : "0x0",
  "filename" : "mscorlib.dll",
  "sizeofimage" : "0x470000",
  "timestamp" : "0xd0713de6",
  "il_offset" : "0x00000"
 }
,
{
  "is_managed" : "true",
  "guid" : "612A2C65-AAF8-43D6-98F8-D38B2AD7654A",
  "token" : "0x00000",
  "native_offset" : "0x0",
  "filename" : "mscorlib.dll",
  "sizeofimage" : "0x470000",
  "timestamp" : "0xd0713de6",
  "il_offset" : "0x00000"
 }
,
{
  "is_managed" : "false",
  "native_address" : "0x13d6958e0",
  "native_offset" : "0x00000"
 }
,
{
  "is_managed" : "false",
  "native_address" : "0x13d81b6a8",
  "native_offset" : "0x00000"
 }
,
{
  "is_managed" : "false",
  "native_address" : "0x13d81d2a4",
  "native_offset" : "0x00000"
 }
,
{
  "is_managed" : "false",
  "native_address" : "0x13d83d5e8",
  "native_offset" : "0x00000"
 }
,
{
  "is_managed" : "false",
  "native_address" : "0x13d83d3a0",
  "native_offset" : "0x00000"
 }
,
{
  "is_managed" : "false",
  "native_address" : "0x13d8bccb0",
  "native_offset" : "0x00000"
 }
,
{
  "is_managed" : "false",
  "native_address" : "0x13d8bcc38",
  "native_offset" : "0x00000"
 }
,
{
  "is_managed" : "false",
  "native_address" : "0x1c41b426c",
  "native_offset" : "0x00000"
 }
,
{
  "is_managed" : "false",
  "native_address" : "0x1c41af08c",
  "native_offset" : "0x00000"
 }

]
},
{
"is_managed" : false,
"offset_free_hash" : "0x0",
"offset_rich_hash" : "0x0",
"crashed" : false,
"native_thread_id" : "0x298b1f000",
"thread_info_addr" : "0x2a867a000",
"thread_name" : "tid_3b60b",
"ctx" : {
  "IP" : "0x1c41768ec",
  "SP" : "0x298b1ed80",
  "BP" : "0x298b1ed90"
},
"unmanaged_frames" : [
{
  "is_managed" : "false",
  "native_address" : "0x13d705c4c",
  "native_offset" : "0x00000"
 }
,
{
  "is_managed" : "false",
  "native_address" : "0x13d83c788",
  "native_offset" : "0x00000"
 }
,
{
  "is_managed" : "false",
  "native_address" : "0x13d83cae4",
  "native_offset" : "0x00000"
 }
,
{
  "is_managed" : "false",
  "native_address" : "0x13d83c8ac",
  "native_offset" : "0x00000"
 }
,
{
  "is_managed" : "false",
  "native_address" : "0x13d746bd4",
  "native_offset" : "0x00000"
 }
,
{
  "is_managed" : "false",
  "native_address" : "0x1c41cb4a4",
  "native_offset" : "0x00000"
 }
,
{
  "is_managed" : "false",
  "native_address" : "0x1c3ff0750",
  "native_offset" : "0x00000"
 }
,
{
  "is_managed" : "false",
  "native_address" : "0x1c3ff0df8",
  "native_offset" : "0x00000"
 }
,
{
  "is_managed" : "false",
  "native_address" : "0x107163d38",
  "native_offset" : "0x00000"
 }
,
{
  "is_managed" : "false",
  "native_address" : "0x104ca75f0",
  "native_offset" : "0x00000"
 }
,
{
  "is_managed" : "false",
  "native_address" : "0x105053470",
  "native_offset" : "0x00000"
 }
,
{
  "is_managed" : "false",
  "native_address" : "0x10505340c",
  "native_offset" : "0x00000"
 }
,
{
  "is_managed" : "false",
  "native_address" : "0x1051d9ae8",
  "native_offset" : "0x00000"
 }
,
{
  "is_managed" : "false",
  "native_address" : "0x1c41b426c",
  "native_offset" : "0x00000"
 }
,
{
  "is_managed" : "false",
  "native_address" : "0x1c41af08c",
  "native_offset" : "0x00000"
 }

]
},
{
"is_managed" : false,
"offset_free_hash" : "0x0",
"offset_rich_hash" : "0x0",
"crashed" : false,
"native_thread_id" : "0x2c7cd3000",
"thread_info_addr" : "0x13f6dd800",
"thread_name" : "Thread Pool I/O Selector",
"ctx" : {
  "IP" : "0x1c4181598",
  "SP" : "0x2c7cd2ae0",
  "BP" : "0x2c7cd2ce0"
},
"unmanaged_frames" : [
{
  "is_managed" : "false",
  "native_address" : "0x13d705c4c",
  "native_offset" : "0x00000"
 }
,
{
  "is_managed" : "false",
  "native_address" : "0x13d83c788",
  "native_offset" : "0x00000"
 }
,
{
  "is_managed" : "false",
  "native_address" : "0x13d83cae4",
  "native_offset" : "0x00000"
 }
,
{
  "is_managed" : "false",
  "native_address" : "0x13d83c8ac",
  "native_offset" : "0x00000"
 }
,
{
  "is_managed" : "false",
  "native_address" : "0x13d746bd4",
  "native_offset" : "0x00000"
 }
,
{
  "is_managed" : "false",
  "native_address" : "0x1c41cb4a4",
  "native_offset" : "0x00000"
 }
,
{
  "is_managed" : "false",
  "native_address" : "0x13d88e8ac",
  "native_offset" : "0x00000"
 }
,
{
  "is_managed" : "false",
  "native_address" : "0x13d841cbc",
  "native_offset" : "0x00000"
 }
,
{
  "is_managed" : "false",
  "native_address" : "0x13d8416d4",
  "native_offset" : "0x00000"
 }
,
{
  "is_managed" : "false",
  "native_address" : "0x13d83d4f4",
  "native_offset" : "0x00000"
 }
,
{
  "is_managed" : "false",
  "native_address" : "0x13d83d3a0",
  "native_offset" : "0x00000"
 }
,
{
  "is_managed" : "false",
  "native_address" : "0x13d8bccb0",
  "native_offset" : "0x00000"
 }
,
{
  "is_managed" : "false",
  "native_address" : "0x13d8bcc38",
  "native_offset" : "0x00000"
 }
,
{
  "is_managed" : "false",
  "native_address" : "0x1c41b426c",
  "native_offset" : "0x00000"
 }
,
{
  "is_managed" : "false",
  "native_address" : "0x1c41af08c",
  "native_offset" : "0x00000"
 }

]
},
{
"is_managed" : false,
"offset_free_hash" : "0x0",
"offset_rich_hash" : "0x0",
"crashed" : false,
"native_thread_id" : "0x29e64b000",
"thread_info_addr" : "0x29a0a2a00",
"thread_name" : "Thread Pool Worker",
"ctx" : {
  "IP" : "0x1c4176904",
  "SP" : "0x29e64adb0",
  "BP" : "0x29e64ae50"
},
"unmanaged_frames" : [
{
  "is_managed" : "false",
  "native_address" : "0x13d705c4c",
  "native_offset" : "0x00000"
 }
,
{
  "is_managed" : "false",
  "native_address" : "0x13d83c788",
  "native_offset" : "0x00000"
 }
,
{
  "is_managed" : "false",
  "native_address" : "0x13d83cae4",
  "native_offset" : "0x00000"
 }
,
{
  "is_managed" : "false",
  "native_address" : "0x13d83c8ac",
  "native_offset" : "0x00000"
 }
,
{
  "is_managed" : "false",
  "native_address" : "0x13d746bd4",
  "native_offset" : "0x00000"
 }
,
{
  "is_managed" : "false",
  "native_address" : "0x1c41cb4a4",
  "native_offset" : "0x00000"
 }
,
{
  "is_managed" : "false",
  "native_address" : "0x13d794c70",
  "native_offset" : "0x00000"
 }
,
{
  "is_managed" : "false",
  "native_address" : "0x13d83d4f4",
  "native_offset" : "0x00000"
 }
,
{
  "is_managed" : "false",
  "native_address" : "0x13d83d3a0",
  "native_offset" : "0x00000"
 }
,
{
  "is_managed" : "false",
  "native_address" : "0x13d8bccb0",
  "native_offset" : "0x00000"
 }
,
{
  "is_managed" : "false",
  "native_address" : "0x13d8bcc38",
  "native_offset" : "0x00000"
 }
,
{
  "is_managed" : "false",
  "native_address" : "0x1c41b426c",
  "native_offset" : "0x00000"
 }
,
{
  "is_managed" : "false",
  "native_address" : "0x1c41af08c",
  "native_offset" : "0x00000"
 }

]
},
{
"is_managed" : false,
"offset_free_hash" : "0x0",
"offset_rich_hash" : "0x0",
"crashed" : false,
"native_thread_id" : "0x17dcbb000",
"thread_info_addr" : "0x15a0d7c00",
"thread_name" : "Finalizer",
"ctx" : {
  "IP" : "0x1c41768ec",
  "SP" : "0x17dcbadd0",
  "BP" : "0x17dcbae50"
},
"unmanaged_frames" : [
{
  "is_managed" : "false",
  "native_address" : "0x13d705c4c",
  "native_offset" : "0x00000"
 }
,
{
  "is_managed" : "false",
  "native_address" : "0x13d83c788",
  "native_offset" : "0x00000"
 }
,
{
  "is_managed" : "false",
  "native_address" : "0x13d83cae4",
  "native_offset" : "0x00000"
 }
,
{
  "is_managed" : "false",
  "native_address" : "0x13d83c8ac",
  "native_offset" : "0x00000"
 }
,
{
  "is_managed" : "false",
  "native_address" : "0x13d746bd4",
  "native_offset" : "0x00000"
 }
,
{
  "is_managed" : "false",
  "native_address" : "0x1c41cb4a4",
  "native_offset" : "0x00000"
 }
,
{
  "is_managed" : "false",
  "native_address" : "0x13d876294",
  "native_offset" : "0x00000"
 }
,
{
  "is_managed" : "false",
  "native_address" : "0x13d83d4f4",
  "native_offset" : "0x00000"
 }
,
{
  "is_managed" : "false",
  "native_address" : "0x13d83d3a0",
  "native_offset" : "0x00000"
 }
,
{
  "is_managed" : "false",
  "native_address" : "0x13d8bccb0",
  "native_offset" : "0x00000"
 }
,
{
  "is_managed" : "false",
  "native_address" : "0x13d8bcc38",
  "native_offset" : "0x00000"
 }
,
{
  "is_managed" : "false",
  "native_address" : "0x1c41b426c",
  "native_offset" : "0x00000"
 }
,
{
  "is_managed" : "false",
  "native_address" : "0x1c41af08c",
  "native_offset" : "0x00000"
 }

]
}
]
}